image_ascii/__init__.py
image_ascii/convert.py
image_ascii-0.1.0.dist-info/LICENSE
image_ascii-0.1.0.dist-info/METADATA
image_ascii-0.1.0.dist-info/WHEEL
image_ascii-0.1.0.dist-info/top_level.txt
image_ascii-0.1.0.dist-info/RECORD
