Metadata-Version: 2.1
Name: image-ascii
Version: 0.1.0
Summary: A package to convert images to ASCII art
Home-page: https://github.com/tianhukj/image-ascii
Author: tianhukj
Author-email: tianhukj@outlook.com
License: UNKNOWN
Platform: UNKNOWN
Classifier: Programming Language :: Python :: 3
Classifier: License :: OSI Approved :: MIT License
Classifier: Operating System :: OS Independent
Requires-Python: >=3.6
Requires-Dist: Pillow
